{
  "sweep_ctc_02": [
    {"compute_itr":20,"sync_time":77287,"async_time":75405,"ctc":0.0215,"speedup":1.0250},
    {"compute_itr":40,"sync_time":77603,"async_time":74169,"ctc":0.0390,"speedup":1.0463},
    {"compute_itr":60,"sync_time":78861,"async_time":74204,"ctc":0.0579,"speedup":1.0628},
    {"compute_itr":80,"sync_time":80179,"async_time":74200,"ctc":0.0769,"speedup":1.0806},
    {"compute_itr":100,"sync_time":81896,"async_time":74183,"ctc":0.0959,"speedup":1.1040},
    {"compute_itr":120,"sync_time":83002,"async_time":74191,"ctc":0.1149,"speedup":1.1188},
    {"compute_itr":140,"sync_time":84681,"async_time":74176,"ctc":0.1339,"speedup":1.1416},
    {"compute_itr":160,"sync_time":86025,"async_time":74179,"ctc":0.1528,"speedup":1.1597},
    {"compute_itr":180,"sync_time":87288,"async_time":74183,"ctc":0.1718,"speedup":1.1767},
    {"compute_itr":200,"sync_time":89038,"async_time":74209,"ctc":0.1907,"speedup":1.1998},
    {"compute_itr":220,"sync_time":90140,"async_time":74224,"ctc":0.2099,"speedup":1.2144},
    {"compute_itr":240,"sync_time":91745,"async_time":74187,"ctc":0.2289,"speedup":1.2367},
    {"compute_itr":260,"sync_time":93192,"async_time":74195,"ctc":0.2477,"speedup":1.2560},
    {"compute_itr":280,"sync_time":94403,"async_time":74195,"ctc":0.2666,"speedup":1.2724},
    {"compute_itr":300,"sync_time":96166,"async_time":74190,"ctc":0.2853,"speedup":1.2962},
    {"compute_itr":320,"sync_time":97308,"async_time":74205,"ctc":0.3048,"speedup":1.3113},
    {"compute_itr":340,"sync_time":98916,"async_time":74190,"ctc":0.3237,"speedup":1.3333},
    {"compute_itr":360,"sync_time":100361,"async_time":74192,"ctc":0.3427,"speedup":1.3527},
    {"compute_itr":380,"sync_time":101509,"async_time":74191,"ctc":0.3615,"speedup":1.3682},
    {"compute_itr":400,"sync_time":103281,"async_time":74219,"ctc":0.3806,"speedup":1.3916},
    {"compute_itr":420,"sync_time":104467,"async_time":74206,"ctc":0.3996,"speedup":1.4078},
    {"compute_itr":440,"sync_time":105905,"async_time":74226,"ctc":0.4186,"speedup":1.4268},
    {"compute_itr":460,"sync_time":107513,"async_time":74188,"ctc":0.4374,"speedup":1.4492},
    {"compute_itr":480,"sync_time":108644,"async_time":74212,"ctc":0.4564,"speedup":1.4640},
    {"compute_itr":500,"sync_time":110386,"async_time":74215,"ctc":0.4756,"speedup":1.4874},
    {"compute_itr":520,"sync_time":111636,"async_time":74229,"ctc":0.4943,"speedup":1.5039},
    {"compute_itr":540,"sync_time":112997,"async_time":74218,"ctc":0.5130,"speedup":1.5225},
    {"compute_itr":560,"sync_time":114664,"async_time":74214,"ctc":0.5323,"speedup":1.5450},
    {"compute_itr":580,"sync_time":115764,"async_time":74214,"ctc":0.5515,"speedup":1.5599},
    {"compute_itr":600,"sync_time":117456,"async_time":74358,"ctc":0.5704,"speedup":1.5796},
    {"compute_itr":620,"sync_time":118796,"async_time":74238,"ctc":0.5890,"speedup":1.6002},
    {"compute_itr":640,"sync_time":120061,"async_time":74209,"ctc":0.6081,"speedup":1.6179},
    {"compute_itr":660,"sync_time":121813,"async_time":74232,"ctc":0.6274,"speedup":1.6410},
    {"compute_itr":680,"sync_time":122919,"async_time":74200,"ctc":0.6460,"speedup":1.6566},
    {"compute_itr":700,"sync_time":124614,"async_time":74278,"ctc":0.6654,"speedup":1.6777},
    {"compute_itr":720,"sync_time":125966,"async_time":74318,"ctc":0.6841,"speedup":1.6950},
    {"compute_itr":740,"sync_time":127230,"async_time":74282,"ctc":0.7027,"speedup":1.7128},
    {"compute_itr":760,"sync_time":128974,"async_time":74275,"ctc":0.7220,"speedup":1.7364},
    {"compute_itr":780,"sync_time":130094,"async_time":74314,"ctc":0.7411,"speedup":1.7506},
    {"compute_itr":800,"sync_time":131711,"async_time":74308,"ctc":0.7597,"speedup":1.7725},
    {"compute_itr":820,"sync_time":133128,"async_time":74310,"ctc":0.7792,"speedup":1.7915},
    {"compute_itr":840,"sync_time":134367,"async_time":74289,"ctc":0.7975,"speedup":1.8087},
    {"compute_itr":860,"sync_time":136125,"async_time":74723,"ctc":0.8167,"speedup":1.8217},
    {"compute_itr":880,"sync_time":137276,"async_time":75694,"ctc":0.8364,"speedup":1.8136},
    {"compute_itr":900,"sync_time":138783,"async_time":77133,"ctc":0.8546,"speedup":1.7993},
    {"compute_itr":920,"sync_time":140297,"async_time":78604,"ctc":0.8733,"speedup":1.7849},
    {"compute_itr":940,"sync_time":141450,"async_time":80057,"ctc":0.8926,"speedup":1.7669},
    {"compute_itr":960,"sync_time":143229,"async_time":81492,"ctc":0.9114,"speedup":1.7576},
    {"compute_itr":980,"sync_time":144401,"async_time":82974,"ctc":0.9309,"speedup":1.7403},
    {"compute_itr":1000,"sync_time":145826,"async_time":84365,"ctc":0.9493,"speedup":1.7285},
    {"compute_itr":1020,"sync_time":147464,"async_time":85792,"ctc":0.9682,"speedup":1.7189},
    {"compute_itr":1040,"sync_time":148561,"async_time":87242,"ctc":0.9878,"speedup":1.7029},
    {"compute_itr":1060,"sync_time":150328,"async_time":88721,"ctc":1.0066,"speedup":1.6944},
    {"compute_itr":1080,"sync_time":151707,"async_time":90138,"ctc":1.0259,"speedup":1.6831},
    {"compute_itr":1100,"sync_time":152943,"async_time":91572,"ctc":1.0446,"speedup":1.6702},
    {"compute_itr":1120,"sync_time":154609,"async_time":93019,"ctc":1.0629,"speedup":1.6621},
    {"compute_itr":1140,"sync_time":155693,"async_time":94489,"ctc":1.0822,"speedup":1.6477},
    {"compute_itr":1160,"sync_time":157411,"async_time":95920,"ctc":1.1006,"speedup":1.6411},
    {"compute_itr":1180,"sync_time":158732,"async_time":97357,"ctc":1.1208,"speedup":1.6304},
    {"compute_itr":1200,"sync_time":160024,"async_time":98778,"ctc":1.1396,"speedup":1.6200},
    {"compute_itr":1220,"sync_time":161743,"async_time":100226,"ctc":1.1584,"speedup":1.6138},
    {"compute_itr":1240,"sync_time":162853,"async_time":101671,"ctc":1.1775,"speedup":1.6018},
    {"compute_itr":1260,"sync_time":164509,"async_time":103128,"ctc":1.1964,"speedup":1.5952},
    {"compute_itr":1280,"sync_time":165942,"async_time":104530,"ctc":1.2151,"speedup":1.5875},
    {"compute_itr":1300,"sync_time":167125,"async_time":106002,"ctc":1.2363,"speedup":1.5766},
    {"compute_itr":1320,"sync_time":168894,"async_time":107419,"ctc":1.2531,"speedup":1.5723},
    {"compute_itr":1340,"sync_time":170012,"async_time":108861,"ctc":1.2716,"speedup":1.5617},
    {"compute_itr":1360,"sync_time":171588,"async_time":110304,"ctc":1.2911,"speedup":1.5556},
    {"compute_itr":1380,"sync_time":173067,"async_time":111766,"ctc":1.3094,"speedup":1.5485},
    {"compute_itr":1400,"sync_time":174238,"async_time":113222,"ctc":1.3288,"speedup":1.5389},
    {"compute_itr":1420,"sync_time":176022,"async_time":114675,"ctc":1.3480,"speedup":1.5350},
    {"compute_itr":1440,"sync_time":177179,"async_time":116146,"ctc":1.3670,"speedup":1.5255},
    {"compute_itr":1460,"sync_time":178655,"async_time":117535,"ctc":1.3857,"speedup":1.5200},
    {"compute_itr":1480,"sync_time":180230,"async_time":118996,"ctc":1.4051,"speedup":1.5146},
    {"compute_itr":1500,"sync_time":181352,"async_time":120422,"ctc":1.4264,"speedup":1.5060},
    {"compute_itr":1520,"sync_time":183145,"async_time":121870,"ctc":1.4421,"speedup":1.5028},
    {"compute_itr":1540,"sync_time":184342,"async_time":123303,"ctc":1.4611,"speedup":1.4950},
    {"compute_itr":1560,"sync_time":185728,"async_time":124752,"ctc":1.4798,"speedup":1.4888},
    {"compute_itr":1580,"sync_time":187387,"async_time":126239,"ctc":1.4996,"speedup":1.4844},
    {"compute_itr":1600,"sync_time":188484,"async_time":127627,"ctc":1.5185,"speedup":1.4768},
    {"compute_itr":1620,"sync_time":190202,"async_time":129076,"ctc":1.5376,"speedup":1.4736},
    {"compute_itr":1640,"sync_time":191502,"async_time":130516,"ctc":1.5563,"speedup":1.4673},
    {"compute_itr":1660,"sync_time":192815,"async_time":131963,"ctc":1.5754,"speedup":1.4611},
    {"compute_itr":1680,"sync_time":194678,"async_time":133406,"ctc":1.5952,"speedup":1.4593},
    {"compute_itr":1700,"sync_time":195623,"async_time":134854,"ctc":1.6129,"speedup":1.4506},
    {"compute_itr":1720,"sync_time":197293,"async_time":136285,"ctc":1.6320,"speedup":1.4477},
    {"compute_itr":1740,"sync_time":198671,"async_time":137738,"ctc":1.6513,"speedup":1.4424},
    {"compute_itr":1760,"sync_time":199908,"async_time":139176,"ctc":1.6704,"speedup":1.4364},
    {"compute_itr":1780,"sync_time":201669,"async_time":140598,"ctc":1.6897,"speedup":1.4344},
    {"compute_itr":1800,"sync_time":202778,"async_time":142028,"ctc":1.7081,"speedup":1.4277},
    {"compute_itr":1820,"sync_time":204484,"async_time":144236,"ctc":1.7268,"speedup":1.4177},
    {"compute_itr":1840,"sync_time":206680,"async_time":145693,"ctc":1.7545,"speedup":1.4186},
    {"compute_itr":1860,"sync_time":208036,"async_time":147138,"ctc":1.7742,"speedup":1.4139},
    {"compute_itr":1880,"sync_time":209300,"async_time":148606,"ctc":1.7937,"speedup":1.4084},
    {"compute_itr":1900,"sync_time":210942,"async_time":150022,"ctc":1.8121,"speedup":1.4061},
    {"compute_itr":1920,"sync_time":212075,"async_time":151497,"ctc":1.8314,"speedup":1.3999},
    {"compute_itr":1940,"sync_time":213826,"async_time":152951,"ctc":1.8510,"speedup":1.3980},
    {"compute_itr":1960,"sync_time":215077,"async_time":154398,"ctc":1.8700,"speedup":1.3930},
    {"compute_itr":1980,"sync_time":216500,"async_time":155831,"ctc":1.8892,"speedup":1.3893},
    {"compute_itr":2000,"sync_time":218114,"async_time":157298,"ctc":1.9086,"speedup":1.3866}
  ]
}
